[
    {
        "id": 133,
        "category_name": "Mũ Lưỡi Trai Nam",
        "description": "Mũ lưỡi trai hay nón kết là một loại mũ được phổ biến rộng rãi ở nhiều quốc gia trên thế giới",
        "imageUrl": "https://mcdn.nhanh.vn/store/7534/ps/20210121/20121389_1000x1000.JPG",
        "products": [
            {
                "id": 251,
                "name": "jkl",
                "imageURL": "httt",
                "price": 451.0,
                "description": "jkl"
            },
            {
                "id": 174,
                "name": "jordan343",
                "imageURL": "https://images-cn.ssl-images-amazon.cn/images/G/28/HUHE/GS/2021/PC_GW_DialUp/arc_379304._SY304_CB657018231_.jpg",
                "price": 2342.0,
                "description": "qasddessa"
            }
        ]
    },
    {
        "id": 103,
        "category_name": "Laptop Asus",
        "description": "Laptop Asus Gaming ROG Strix G513IH-HN015W (R7 4800H/8GB RAM/512GB SSD/15.6 FHD 144hz/GTX1650 4GB/Win11/Xám)",
        "imageUrl": "https://bizweb.dktcdn.net/thumb/large/100/082/878/products/60425-laptop-asus-gaming-rog-strix-g513qm-hf389t-xam-10-1b2f3471-13e1-4760-9733-4a5f2d7a9927-c3c39d3d-5383-4f70-98ee-aca93f842d6e.png?v=1644462454247",
        "products": []
    },
    {
        "id": 185,
        "category_name": "Manteau",
        "description": "Ici vous trouverez tous vos Manteaus ! ",
        "imageUrl": "https://media.vertbaudet.fr/Pictures/vertbaudet/106466/manteau-fille-en-drap-de-laine.jpg",
        "products": [
            {
                "id": 165,
                "name": "adidas33",
                "imageURL": null,
                "price": 120.0,
                "description": "breal"
            },
            {
                "id": 661,
                "name": "Mia",
                "imageURL": null,
                "price": 1.0E19,
                "description": "Tient très chaud"
            },
            {
                "id": 163,
                "name": "adidas33",
                "imageURL": null,
                "price": 120.0,
                "description": null
            },
            {
                "id": 20,
                "name": "Samsung Galaxy S22",
                "imageURL": "https://s6.jpg.cm/2022/02/22/LfHEqk.jpg",
                "price": 1500.0,
                "description": "Samsung Galaxy S22 Ultra 5G ; Internal, 128GB 8GB RAM, 256GB 12GB RAM, 512GB 12GB RAM, 1TB 12GB RAM ; Main Camera, Quad ; Features, LED flash, auto-HDR, panorama."
            }
        ]
    }
]